odoo/addons/sale_order_product_recommendation_elaboration/README.rst
odoo/addons/sale_order_product_recommendation_elaboration/__init__.py
odoo/addons/sale_order_product_recommendation_elaboration/__manifest__.py
odoo/addons/sale_order_product_recommendation_elaboration/i18n/it.po
odoo/addons/sale_order_product_recommendation_elaboration/i18n/sale_order_product_recommendation_elaboration.pot
odoo/addons/sale_order_product_recommendation_elaboration/readme/CONTEXT.md
odoo/addons/sale_order_product_recommendation_elaboration/readme/CONTRIBUTORS.md
odoo/addons/sale_order_product_recommendation_elaboration/readme/CREDITS.md
odoo/addons/sale_order_product_recommendation_elaboration/readme/DESCRIPTION.md
odoo/addons/sale_order_product_recommendation_elaboration/readme/USAGE.md
odoo/addons/sale_order_product_recommendation_elaboration/static/description/icon.png
odoo/addons/sale_order_product_recommendation_elaboration/static/description/index.html
odoo/addons/sale_order_product_recommendation_elaboration/tests/__init__.py
odoo/addons/sale_order_product_recommendation_elaboration/tests/test_sale_order_recommendation.py
odoo/addons/sale_order_product_recommendation_elaboration/wizards/__init__.py
odoo/addons/sale_order_product_recommendation_elaboration/wizards/sale_order_recommendation.py
odoo/addons/sale_order_product_recommendation_elaboration/wizards/sale_order_recommendation_view.xml
odoo_addon_sale_order_product_recommendation_elaboration-16.0.2.0.1.dist-info/METADATA
odoo_addon_sale_order_product_recommendation_elaboration-16.0.2.0.1.dist-info/WHEEL
odoo_addon_sale_order_product_recommendation_elaboration-16.0.2.0.1.dist-info/top_level.txt
odoo_addon_sale_order_product_recommendation_elaboration-16.0.2.0.1.dist-info/RECORD
